genrat_netce/__init__.py
genrat_netce/main.cpython-311-darwin.so
genrat_netce-0.1.dist-info/LICENCE.txt
genrat_netce-0.1.dist-info/METADATA
genrat_netce-0.1.dist-info/WHEEL
genrat_netce-0.1.dist-info/top_level.txt
genrat_netce-0.1.dist-info/RECORD
